cache/instructionhasher.v
//This module implements the instruction cache's hashing function.
//It's placed in a separate module to allow for greater flexibility later on.
module instructionhasher(
	addr,
	OUT
	);

input [31:0] addr;
output [5:0] OUT;

wire [28:0] adjustedAddr;
assign adjustedAddr=addr[31:2];

assign OUT=adjustedAddr%64; //Don't bother with associativity yet.

endmodule

RevisionB/instructioncache.v
//This module represents a very simple, small instruction cache.
//The cache exists to increase average bandwidth so that future revisions of the core
//can have nice things, like superscalar execution. 

module instructioncache(memdat, addr, clk, rst, wt, DATOUT, OUTADDR, OUTWAIT);

input [15:0] memdat;
input [31:0] addr;
input clk;
input rst;
input wt;
output [63:0] DATOUT;
output [31:0] OUTADDR;
output OUTWAIT;


//reg [63:0] outDat;
//assign OUT=outDat;
reg [31:0] outAddr;
assign OUTADDR=outAddr;

//Declare the actual cache memory itself.
//Overall, it has 64 4-word lines
reg [63:0] iCache [0:63]; 
reg [31:0] tags [0:63];

wire [5:0] lineSel;
instructionhasher hash(addr, lineSel);

wire [31:0] curLine;
assign curLine=tags[lineSel];
   
assign DATOUT=iCache[lineSel];

//The address should count up by four each time, as the instruction fetch/dispatch unit
//should effectively handle the rest.
   //wire     ow1;
   //assign ow1=(tags[lineSel]>=addr);
   //assign ow2=(addr<(tags[lineSel]+4);
assign OUTWAIT=~((addr>=tags[lineSel])&&(addr<(tags[lineSel]+4)));

reg [3:0] stateCtr;

//This exists basically just to fetch data from memory.
always@(posedge clk) begin
	if(OUTWAIT) begin
		//Set address lines for the first byte:
		if(stateCtr==0) begin
			outAddr<=addr;

			if(~wt) begin
				stateCtr<=stateCtr+1;
			end
		end

		else if(stateCtr==1) begin
			iCache[lineSel][15:0]<=memdat;
			outAddr<=addr+1;
			
			//Note: if necessary, I will break the state counter off into its own functional unit
			//so that I don't have to repeat so much code and waste so many gates.
			if(~wt) begin
				stateCtr<=stateCtr+1;
			end
		end

		else if(stateCtr==2) begin
			iCache[lineSel][31:16]<=memdat;
			outAddr<=addr+2;

			if(~wt) begin
				stateCtr<=stateCtr+1;
			end
		end

		else if(stateCtr==3) begin
			iCache[lineSel][47:32]<=memdat;
			outAddr<=addr+3;

			if(~wt) begin
				stateCtr<=stateCtr+1;
			end
		end

		else if(stateCtr==4) begin
			iCache[lineSel][63:48]<=memdat;
			tags[lineSel]<=addr;

			if(~wt) begin
				stateCtr<=0;
			end
		end
	end
end // always@ (posedge clk)

reg [10:0] i;
   
initial begin
   for(i=0;i<64;i=i+1) begin
      tags[i]=32'hF0000000;
      
   end

   stateCtr=0;
   
end

endmodule

cache/instructioncache_tb.v
//This defines a very simple testbench for the instruction cacher.
//It is intended to work with "real world" access data in order to provide statistics for
//hits, misses, and whether the cache actually flipping works.

module instructioncache_tb();

reg [31:0] requestedAddresses [0:5000];
reg [31:0] addressCounter;
wire [31:0] selectedAddress;
wire [15:0] memDat;
reg clk;
wire rst;
wire wt;
wire [63:0] outWire;
wire [31:0] outAddr;
wire cachewt;

assign selectedAddress=requestedAddresses[addressCounter];
assign memDat=outAddr[15:0];
assign rst=0;
assign wt=0;

instructioncache icache(memDat, selectedAddress, clk, rst, wt, outWire, outAddr, cachewt);
reg [31:0] numMisses;
reg [31:0] numHits;
   
reg [31:0] numCycles;
reg [31:0] numwtCycles;

initial begin
	addressCounter=0;
	$readmemb("memaccess.txt", requestedAddresses);
	clk=0;
	numMisses=0;
	numCycles=0;
   numwtCycles=0;
   numHits=0;
   
   
end



always begin
	#1 clk=~clk;
	
end

always@(posedge cachewt) begin
	numMisses<=numMisses+1;
end

always@(posedge clk) begin
	numCycles<=numCycles+1;
	if(~cachewt) begin
		addressCounter<=addressCounter+1;
	   numHits=numHits+1;
	   
	end

	else begin
		numwtCycles<=numwtCycles+1;
	end
end

initial begin
   	$display("Number of misses: %d", numMisses);
	$display("Number of cycles: %d", numCycles);
	$display("Number of cycles stalled: %d", numwtCycles);
	$dumpfile("instructioncache_tb.vcd");
	$dumpvars;
end

initial
  #4000 $finish;
   
endmodule

cache/instructioncache_tb.vcd
$date
	Thu Dec 24 15:05:45 2015
$end
$version
	Icarus Verilog
$end
$timescale
	1s
$end
$scope module instructioncache_tb $end
$var wire 1 ! rst $end
$var wire 32 " selectedAddress [31:0] $end
$var wire 1 # wt $end
$var wire 64 $ outWire [63:0] $end
$var wire 32 % outAddr [31:0] $end
$var wire 16 & memDat [15:0] $end
$var wire 1 ' cachewt $end
$var reg 32 ( addressCounter [31:0] $end
$var reg 1 ) clk $end
$var reg 32 * numCycles [31:0] $end
$var reg 32 + numHits [31:0] $end
$var reg 32 , numMisses [31:0] $end
$var reg 32 - numwtCycles [31:0] $end
$scope module icache $end
$var wire 64 . DATOUT [63:0] $end
$var wire 1 ' OUTWAIT $end
$var wire 32 / addr [31:0] $end
$var wire 1 ) clk $end
$var wire 32 0 curLine [31:0] $end
$var wire 16 1 memdat [15:0] $end
$var wire 1 ! rst $end
$var wire 1 # wt $end
$var wire 6 2 lineSel [5:0] $end
$var wire 32 3 OUTADDR [31:0] $end
$var reg 11 4 i [10:0] $end
$var reg 32 5 outAddr [31:0] $end
$var reg 4 6 stateCtr [3:0] $end
$scope module hash $end
$var wire 32 7 addr [31:0] $end
$var wire 29 8 adjustedAddr [28:0] $end
$var wire 6 9 OUT [5:0] $end
$upscope $end
$upscope $end
$upscope $end
$enddefinitions $end
#0
$dumpvars
b0 9
b0 8
b0 7
b0 6
bx 5
b1000000 4
bx 3
b0 2
bx 1
b11110000000000000000000000000000 0
b0 /
bx .
b0 -
b1 ,
b0 +
b0 *
0)
b0 (
1'
bx &
bx %
bx $
0#
b0 "
0!
$end
#1
b0 &
b0 1
b1 6
b0 %
b0 3
b0 5
b1 -
b1 *
1)
#2
0)
#3
b1 &
b1 1
b10 -
b10 *
b10 6
b1 %
b1 3
b1 5
bx0000000000000000 $
bx0000000000000000 .
1)
#4
0)
#5
b10 &
b10 1
b11 6
b10 %
b10 3
b10 5
bx00000000000000010000000000000000 $
bx00000000000000010000000000000000 .
b11 -
b11 *
1)
#6
0)
#7
b11 &
b11 1
b100 -
b100 *
b100 6
b11 %
b11 3
b11 5
bx000000000000001000000000000000010000000000000000 $
bx000000000000001000000000000000010000000000000000 .
1)
#8
0)
#9
0'
b0 6
b0 0
b11000000000000001000000000000000010000000000000000 $
b11000000000000001000000000000000010000000000000000 .
b101 -
b101 *
1)
#10
0)
#11
b1 "
b1 /
b1 7
b1 (
b110 *
b1 +
1)
#12
0)
#13
b10 (
b111 *
b10 +
1)
#14
0)
#15
b10 "
b10 /
b10 7
b11 (
b1000 *
b11 +
1)
#16
0)
#17
b100 (
b1001 *
b100 +
1)
#18
0)
#19
b11 "
b11 /
b11 7
b101 (
b1010 *
b101 +
1)
#20
0)
#21
b110 (
b1011 *
b110 +
1)
#22
0)
#23
b10 ,
bx $
bx .
b11110000000000000000000000000000 0
b1 2
b1 9
1'
b1 8
b100 "
b100 /
b100 7
b111 (
b1100 *
b111 +
1)
#24
0)
#25
b100 &
b100 1
b1 6
b100 %
b100 3
b100 5
b110 -
b1101 *
1)
#26
0)
#27
b101 &
b101 1
b111 -
b1110 *
b10 6
b101 %
b101 3
b101 5
bx0000000000000100 $
bx0000000000000100 .
1)
#28
0)
#29
b110 &
b110 1
b11 6
b110 %
b110 3
b110 5
bx00000000000001010000000000000100 $
bx00000000000001010000000000000100 .
b1000 -
b1111 *
1)
#30
0)
#31
b111 &
b111 1
b1001 -
b10000 *
b100 6
b111 %
b111 3
b111 5
bx000000000000011000000000000001010000000000000100 $
bx000000000000011000000000000001010000000000000100 .
1)
#32
0)
#33
0'
b0 6
b100 0
b111000000000000011000000000000001010000000000000100 $
b111000000000000011000000000000001010000000000000100 .
b1010 -
b10001 *
1)
#34
0)
#35
b1000 (
b10010 *
b1000 +
1)
#36
0)
#37
b101 "
b101 /
b101 7
b1001 (
b10011 *
b1001 +
1)
#38
0)
#39
b1010 (
b10100 *
b1010 +
1)
#40
0)
#41
b110 "
b110 /
b110 7
b1011 (
b10101 *
b1011 +
1)
#42
0)
#43
b1100 (
b10110 *
b1100 +
1)
#44
0)
#45
b111 "
b111 /
b111 7
b1101 (
b10111 *
b1101 +
1)
#46
0)
#47
b1110 (
b11000 *
b1110 +
1)
#48
0)
#49
b11 ,
bx $
bx .
b11110000000000000000000000000000 0
b10 2
b10 9
1'
b10 8
b1000 "
b1000 /
b1000 7
b1111 (
b11001 *
b1111 +
1)
#50
0)
#51
b1000 &
b1000 1
b1011 -
b11010 *
b1 6
b1000 %
b1000 3
b1000 5
1)
#52
0)
#53
b1001 &
b1001 1
b10 6
b1001 %
b1001 3
b1001 5
bx0000000000001000 $
bx0000000000001000 .
b1100 -
b11011 *
1)
#54
0)
#55
b1010 &
b1010 1
b1101 -
b11100 *
b11 6
b1010 %
b1010 3
b1010 5
bx00000000000010010000000000001000 $
bx00000000000010010000000000001000 .
1)
#56
0)
#57
b1011 &
b1011 1
b100 6
b1011 %
b1011 3
b1011 5
bx000000000000101000000000000010010000000000001000 $
bx000000000000101000000000000010010000000000001000 .
b1110 -
b11101 *
1)
#58
0)
#59
0'
b1111 -
b11110 *
b0 6
b1000 0
b1011000000000000101000000000000010010000000000001000 $
b1011000000000000101000000000000010010000000000001000 .
1)
#60
0)
#61
b10000 (
b11111 *
b10000 +
1)
#62
0)
#63
b1001 "
b1001 /
b1001 7
b10001 (
b100000 *
b10001 +
1)
#64
0)
#65
b10010 (
b100001 *
b10010 +
1)
#66
0)
#67
b1010 "
b1010 /
b1010 7
b10011 (
b100010 *
b10011 +
1)
#68
0)
#69
b10100 (
b100011 *
b10100 +
1)
#70
0)
#71
b10101 (
b100100 *
b10101 +
1)
#72
0)
#73
b10110 (
b100101 *
b10110 +
1)
#74
0)
#75
b10111 (
b100110 *
b10111 +
1)
#76
0)
#77
b11000 (
b100111 *
b11000 +
1)
#78
0)
#79
b1011 "
b1011 /
b1011 7
b11001 (
b101000 *
b11001 +
1)
#80
0)
#81
b11010 (
b101001 *
b11010 +
1)
#82
0)
#83
b11011 (
b101010 *
b11011 +
1)
#84
0)
#85
b11100 (
b101011 *
b11100 +
1)
#86
0)
#87
b11101 (
b101100 *
b11101 +
1)
#88
0)
#89
b11110 (
b101101 *
b11110 +
1)
#90
0)
#91
b11111 (
b101110 *
b11111 +
1)
#92
0)
#93
b100000 (
b101111 *
b100000 +
1)
#94
0)
#95
b100001 (
b110000 *
b100001 +
1)
#96
0)
#97
b100010 (
b110001 *
b100010 +
1)
#98
0)
#99
b100 ,
bx $
bx .
b11110000000000000000000000000000 0
b11 2
b11 9
1'
b11 8
b1100 "
b1100 /
b1100 7
b100011 (
b110010 *
b100011 +
1)
#100
0)
#101
b1100 &
b1100 1
b1 6
b1100 %
b1100 3
b1100 5
b10000 -
b110011 *
1)
#102
0)
#103
b1101 &
b1101 1
b10001 -
b110100 *
b10 6
b1101 %
b1101 3
b1101 5
bx0000000000001100 $
bx0000000000001100 .
1)
#104
0)
#105
b1110 &
b1110 1
b11 6
b1110 %
b1110 3
b1110 5
bx00000000000011010000000000001100 $
bx00000000000011010000000000001100 .
b10010 -
b110101 *
1)
#106
0)
#107
b1111 &
b1111 1
b10011 -
b110110 *
b100 6
b1111 %
b1111 3
b1111 5
bx000000000000111000000000000011010000000000001100 $
bx000000000000111000000000000011010000000000001100 .
1)
#108
0)
#109
0'
b0 6
b1100 0
b1111000000000000111000000000000011010000000000001100 $
b1111000000000000111000000000000011010000000000001100 .
b10100 -
b110111 *
1)
#110
0)
#111
b100100 (
b111000 *
b100100 +
1)
#112
0)
#113
b1101 "
b1101 /
b1101 7
b100101 (
b111001 *
b100101 +
1)
#114
0)
#115
b100110 (
b111010 *
b100110 +
1)
#116
0)
#117
b1110 "
b1110 /
b1110 7
b100111 (
b111011 *
b100111 +
1)
#118
0)
#119
b101000 (
b111100 *
b101000 +
1)
#120
0)
#121
b1111 "
b1111 /
b1111 7
b101001 (
b111101 *
b101001 +
1)
#122
0)
#123
b101010 (
b111110 *
b101010 +
1)
#124
0)
#125
b101 ,
bx $
bx .
b11110000000000000000000000000000 0
b100 2
b100 9
1'
b100 8
b10000 "
b10000 /
b10000 7
b101011 (
b111111 *
b101011 +
1)
#126
0)
#127
b10000 &
b10000 1
b10101 -
b1000000 *
b1 6
b10000 %
b10000 3
b10000 5
1)
#128
0)
#129
b10001 &
b10001 1
b10 6
b10001 %
b10001 3
b10001 5
bx0000000000010000 $
bx0000000000010000 .
b10110 -
b1000001 *
1)
#130
0)
#131
b10010 &
b10010 1
b10111 -
b1000010 *
b11 6
b10010 %
b10010 3
b10010 5
bx00000000000100010000000000010000 $
bx00000000000100010000000000010000 .
1)
#132
0)
#133
b10011 &
b10011 1
b100 6
b10011 %
b10011 3
b10011 5
bx000000000001001000000000000100010000000000010000 $
bx000000000001001000000000000100010000000000010000 .
b11000 -
b1000011 *
1)
#134
0)
#135
0'
b11001 -
b1000100 *
b0 6
b10000 0
b10011000000000001001000000000000100010000000000010000 $
b10011000000000001001000000000000100010000000000010000 .
1)
#136
0)
#137
b101100 (
b1000101 *
b101100 +
1)
#138
0)
#139
b10001 "
b10001 /
b10001 7
b101101 (
b1000110 *
b101101 +
1)
#140
0)
#141
b101110 (
b1000111 *
b101110 +
1)
#142
0)
#143
b101111 (
b1001000 *
b101111 +
1)
#144
0)
#145
b110000 (
b1001001 *
b110000 +
1)
#146
0)
#147
b110 ,
bx $
bx .
b11110000000000000000000000000000 0
b111111 2
b111111 9
1'
b1111111111111 8
b111111111111111 "
b111111111111111 /
b111111111111111 7
b110001 (
b1001010 *
b110001 +
1)
#148
0)
#149
b111111111111111 &
b111111111111111 1
b1 6
b111111111111111 %
b111111111111111 3
b111111111111111 5
b11010 -
b1001011 *
1)
#150
0)
#151
b1000000000000000 &
b1000000000000000 1
b11011 -
b1001100 *
b10 6
b1000000000000000 %
b1000000000000000 3
b1000000000000000 5
bx0111111111111111 $
bx0111111111111111 .
1)
#152
0)
#153
b1000000000000001 &
b1000000000000001 1
b11 6
b1000000000000001 %
b1000000000000001 3
b1000000000000001 5
bx10000000000000000111111111111111 $
bx10000000000000000111111111111111 .
b11100 -
b1001101 *
1)
#154
0)
#155
b1000000000000010 &
b1000000000000010 1
b11101 -
b1001110 *
b100 6
b1000000000000010 %
b1000000000000010 3
b1000000000000010 5
bx100000000000000110000000000000000111111111111111 $
bx100000000000000110000000000000000111111111111111 .
1)
#156
0)
#157
0'
b0 6
b111111111111111 0
b1000000000000010100000000000000110000000000000000111111111111111 $
b1000000000000010100000000000000110000000000000000111111111111111 .
b11110 -
b1001111 *
1)
#158
0)
#159
b110010 (
b1010000 *
b110010 +
1)
#160
0)
#161
b111 ,
bx $
bx .
b11110000000000000000000000000000 0
b10100 2
b10100 9
1'
b10100 8
b1010010 "
b1010010 /
b1010010 7
b110011 (
b1010001 *
b110011 +
1)
#162
0)
#163
b1010010 &
b1010010 1
b11111 -
b1010010 *
b1 6
b1010010 %
b1010010 3
b1010010 5
1)
#164
0)
#165
b1010011 &
b1010011 1
b10 6
b1010011 %
b1010011 3
b1010011 5
bx0000000001010010 $
bx0000000001010010 .
b100000 -
b1010011 *
1)
#166
0)
#167
b1010100 &
b1010100 1
b100001 -
b1010100 *
b11 6
b1010100 %
b1010100 3
b1010100 5
bx00000000010100110000000001010010 $
bx00000000010100110000000001010010 .
1)
#168
0)
#169
b1010101 &
b1010101 1
b100 6
b1010101 %
b1010101 3
b1010101 5
bx000000000101010000000000010100110000000001010010 $
bx000000000101010000000000010100110000000001010010 .
b100010 -
b1010101 *
1)
#170
0)
#171
0'
b100011 -
b1010110 *
b0 6
b1010010 0
b1010101000000000101010000000000010100110000000001010010 $
b1010101000000000101010000000000010100110000000001010010 .
1)
#172
0)
#173
b110100 (
b1010111 *
b110100 +
1)
#174
0)
#175
b1010011 "
b1010011 /
b1010011 7
b110101 (
b1011000 *
b110101 +
1)
#176
0)
#177
b110110 (
b1011001 *
b110110 +
1)
#178
0)
#179
b1000 ,
1'
bx $
bx .
b11110000000000000000000000000000 0
b10101 2
b10101 9
b10101 8
b1010100 "
b1010100 /
b1010100 7
b110111 (
b1011010 *
b110111 +
1)
#180
0)
#181
b1010100 &
b1010100 1
b1 6
b1010100 %
b1010100 3
b1010100 5
b100100 -
b1011011 *
1)
#182
0)
#183
b1010101 &
b1010101 1
b100101 -
b1011100 *
b10 6
b1010101 %
b1010101 3
b1010101 5
bx0000000001010100 $
bx0000000001010100 .
1)
#184
0)
#185
b1010110 &
b1010110 1
b11 6
b1010110 %
b1010110 3
b1010110 5
bx00000000010101010000000001010100 $
bx00000000010101010000000001010100 .
b100110 -
b1011101 *
1)
#186
0)
#187
b1010111 &
b1010111 1
b100111 -
b1011110 *
b100 6
b1010111 %
b1010111 3
b1010111 5
bx000000000101011000000000010101010000000001010100 $
bx000000000101011000000000010101010000000001010100 .
1)
#188
0)
#189
0'
b0 6
b1010100 0
b1010111000000000101011000000000010101010000000001010100 $
b1010111000000000101011000000000010101010000000001010100 .
b101000 -
b1011111 *
1)
#190
0)
#191
b111000 (
b1100000 *
b111000 +
1)
#192
0)
#193
b1010101 "
b1010101 /
b1010101 7
b111001 (
b1100001 *
b111001 +
1)
#194
0)
#195
b111010 (
b1100010 *
b111010 +
1)
#196
0)
#197
b1010110 "
b1010110 /
b1010110 7
b111011 (
b1100011 *
b111011 +
1)
#198
0)
#199
b111100 (
b1100100 *
b111100 +
1)
#200
0)
#201
b1010111 "
b1010111 /
b1010111 7
b111101 (
b1100101 *
b111101 +
1)
#202
0)
#203
b111110 (
b1100110 *
b111110 +
1)
#204
0)
#205
b1001 ,
bx $
bx .
b11110000000000000000000000000000 0
b10110 2
b10110 9
1'
b10110 8
b1011000 "
b1011000 /
b1011000 7
b111111 (
b1100111 *
b111111 +
1)
#206
0)
#207
b1011000 &
b1011000 1
b101001 -
b1101000 *
b1 6
b1011000 %
b1011000 3
b1011000 5
1)
#208
0)
#209
b1011001 &
b1011001 1
b10 6
b1011001 %
b1011001 3
b1011001 5
bx0000000001011000 $
bx0000000001011000 .
b101010 -
b1101001 *
1)
#210
0)
#211
b1011010 &
b1011010 1
b101011 -
b1101010 *
b11 6
b1011010 %
b1011010 3
b1011010 5
bx00000000010110010000000001011000 $
bx00000000010110010000000001011000 .
1)
#212
0)
#213
b1011011 &
b1011011 1
b100 6
b1011011 %
b1011011 3
b1011011 5
bx000000000101101000000000010110010000000001011000 $
bx000000000101101000000000010110010000000001011000 .
b101100 -
b1101011 *
1)
#214
0)
#215
0'
b101101 -
b1101100 *
b0 6
b1011000 0
b1011011000000000101101000000000010110010000000001011000 $
b1011011000000000101101000000000010110010000000001011000 .
1)
#216
0)
#217
b1000000 (
b1101101 *
b1000000 +
1)
#218
0)
#219
b1011001 "
b1011001 /
b1011001 7
b1000001 (
b1101110 *
b1000001 +
1)
#220
0)
#221
b1000010 (
b1101111 *
b1000010 +
1)
#222
0)
#223
b1011010 "
b1011010 /
b1011010 7
b1000011 (
b1110000 *
b1000011 +
1)
#224
0)
#225
b1000100 (
b1110001 *
b1000100 +
1)
#226
0)
#227
b1011011 "
b1011011 /
b1011011 7
b1000101 (
b1110010 *
b1000101 +
1)
#228
0)
#229
b1000110 (
b1110011 *
b1000110 +
1)
#230
0)
#231
b1000111 (
b1110100 *
b1000111 +
1)
#232
0)
#233
b1001000 (
b1110101 *
b1001000 +
1)
#234
0)
#235
b1010 ,
b11000000000000001000000000000000010000000000000000 $
b11000000000000001000000000000000010000000000000000 .
b0 0
b0 2
b0 9
1'
b110000000000000000 8
b11000000000000000000 "
b11000000000000000000 /
b11000000000000000000 7
b1001001 (
b1110110 *
b1001001 +
1)
#236
0)
#237
b0 &
b0 1
b1 6
b11000000000000000000 %
b11000000000000000000 3
b11000000000000000000 5
b101110 -
b1110111 *
1)
#238
0)
#239
b1 &
b1 1
b101111 -
b1111000 *
b10 6
b11000000000000000001 %
b11000000000000000001 3
b11000000000000000001 5
1)
#240
0)
#241
b10 &
b10 1
b11 6
b11000000000000000010 %
b11000000000000000010 3
b11000000000000000010 5
b110000 -
b1111001 *
1)
#242
0)
#243
b11 &
b11 1
b110001 -
b1111010 *
b100 6
b11000000000000000011 %
b11000000000000000011 3
b11000000000000000011 5
1)
#244
0)
#245
0'
b0 6
b11000000000000000000 0
b110010 -
b1111011 *
1)
#246
0)
#247
b1001010 (
b1111100 *
b1001010 +
1)
#248
0)
#249
b1011 ,
b1011011000000000101101000000000010110010000000001011000 $
b1011011000000000101101000000000010110010000000001011000 .
b1011000 0
b10110 2
b10110 9
0'
b10110 8
b1011011 "
b1011011 /
b1011011 7
b1001011 (
b1111101 *
b1001011 +
1)
#250
0)
#251
b1001100 (
b1111110 *
b1001100 +
1)
#252
0)
#253
b1100 ,
bx $
bx .
b11110000000000000000000000000000 0
b10111 2
b10111 9
1'
b10111 8
b1011100 "
b1011100 /
b1011100 7
b1001101 (
b1111111 *
b1001101 +
1)
#254
0)
#255
b1011100 &
b1011100 1
b110011 -
b10000000 *
b1 6
b1011100 %
b1011100 3
b1011100 5
1)
#256
0)
#257
b1011101 &
b1011101 1
b10 6
b1011101 %
b1011101 3
b1011101 5
bx0000000001011100 $
bx0000000001011100 .
b110100 -
b10000001 *
1)
#258
0)
#259
b1011110 &
b1011110 1
b110101 -
b10000010 *
b11 6
b1011110 %
b1011110 3
b1011110 5
bx00000000010111010000000001011100 $
bx00000000010111010000000001011100 .
1)
#260
0)
#261
b1011111 &
b1011111 1
b100 6
b1011111 %
b1011111 3
b1011111 5
bx000000000101111000000000010111010000000001011100 $
bx000000000101111000000000010111010000000001011100 .
b110110 -
b10000011 *
1)
#262
0)
#263
0'
b110111 -
b10000100 *
b0 6
b1011100 0
b1011111000000000101111000000000010111010000000001011100 $
b1011111000000000101111000000000010111010000000001011100 .
1)
#264
0)
#265
b1001110 (
b10000101 *
b1001110 +
1)
#266
0)
#267
b1011101 "
b1011101 /
b1011101 7
b1001111 (
b10000110 *
b1001111 +
1)
#268
0)
#269
b1010000 (
b10000111 *
b1010000 +
1)
#270
0)
#271
b1011110 "
b1011110 /
b1011110 7
b1010001 (
b10001000 *
b1010001 +
1)
#272
0)
#273
b1010010 (
b10001001 *
b1010010 +
1)
#274
0)
#275
b1011111 "
b1011111 /
b1011111 7
b1010011 (
b10001010 *
b1010011 +
1)
#276
0)
#277
b1010100 (
b10001011 *
b1010100 +
1)
#278
0)
#279
b1101 ,
bx $
bx .
b11110000000000000000000000000000 0
b11000 2
b11000 9
1'
b11000 8
b1100000 "
b1100000 /
b1100000 7
b1010101 (
b10001100 *
b1010101 +
1)
#280
0)
#281
b1100000 &
b1100000 1
b1 6
b1100000 %
b1100000 3
b1100000 5
b111000 -
b10001101 *
1)
#282
0)
#283
b1100001 &
b1100001 1
b111001 -
b10001110 *
b10 6
b1100001 %
b1100001 3
b1100001 5
bx0000000001100000 $
bx0000000001100000 .
1)
#284
0)
#285
b1100010 &
b1100010 1
b11 6
b1100010 %
b1100010 3
b1100010 5
bx00000000011000010000000001100000 $
bx00000000011000010000000001100000 .
b111010 -
b10001111 *
1)
#286
0)
#287
b1100011 &
b1100011 1
b111011 -
b10010000 *
b100 6
b1100011 %
b1100011 3
b1100011 5
bx000000000110001000000000011000010000000001100000 $
bx000000000110001000000000011000010000000001100000 .
1)
#288
0)
#289
0'
b0 6
b1100000 0
b1100011000000000110001000000000011000010000000001100000 $
b1100011000000000110001000000000011000010000000001100000 .
b111100 -
b10010001 *
1)
#290
0)
#291
b1010110 (
b10010010 *
b1010110 +
1)
#292
0)
#293
b1100001 "
b1100001 /
b1100001 7
b1010111 (
b10010011 *
b1010111 +
1)
#294
0)
#295
b1011000 (
b10010100 *
b1011000 +
1)
#296
0)
#297
b1100010 "
b1100010 /
b1100010 7
b1011001 (
b10010101 *
b1011001 +
1)
#298
0)
#299
b1011010 (
b10010110 *
b1011010 +
1)
#300
0)
#301
b1100011 "
b1100011 /
b1100011 7
b1011011 (
b10010111 *
b1011011 +
1)
#302
0)
#303
b1011100 (
b10011000 *
b1011100 +
1)
#304
0)
#305
b1110 ,
bx $
bx .
b11110000000000000000000000000000 0
b11001 2
b11001 9
1'
b11001 8
b1100100 "
b1100100 /
b1100100 7
b1011101 (
b10011001 *
b1011101 +
1)
#306
0)
#307
b1100100 &
b1100100 1
b111101 -
b10011010 *
b1 6
b1100100 %
b1100100 3
b1100100 5
1)
#308
0)
#309
b1100101 &
b1100101 1
b10 6
b1100101 %
b1100101 3
b1100101 5
bx0000000001100100 $
bx0000000001100100 .
b111110 -
b10011011 *
1)
#310
0)
#311
b1100110 &
b1100110 1
b111111 -
b10011100 *
b11 6
b1100110 %
b1100110 3
b1100110 5
bx00000000011001010000000001100100 $
bx00000000011001010000000001100100 .
1)
#312
0)
#313
b1100111 &
b1100111 1
b100 6
b1100111 %
b1100111 3
b1100111 5
bx000000000110011000000000011001010000000001100100 $
bx000000000110011000000000011001010000000001100100 .
b1000000 -
b10011101 *
1)
#314
0)
#315
0'
b1000001 -
b10011110 *
b0 6
b1100100 0
b1100111000000000110011000000000011001010000000001100100 $
b1100111000000000110011000000000011001010000000001100100 .
1)
#316
0)
#317
b1011110 (
b10011111 *
b1011110 +
1)
#318
0)
#319
b1100101 "
b1100101 /
b1100101 7
b1011111 (
b10100000 *
b1011111 +
1)
#320
0)
#321
b1100000 (
b10100001 *
b1100000 +
1)
#322
0)
#323
b1100001 (
b10100010 *
b1100001 +
1)
#324
0)
#325
b1100010 (
b10100011 *
b1100010 +
1)
#326
0)
#327
b1111 ,
b11000000000000001000000000000000010000000000000000 $
b11000000000000001000000000000000010000000000000000 .
b11000000000000000000 0
b0 2
b0 9
1'
b11010000000000000000 8
b1101000000000000000000 "
b1101000000000000000000 /
b1101000000000000000000 7
b1100011 (
b10100100 *
b1100011 +
1)
#328
0)
#329
b0 &
b0 1
b1 6
b1101000000000000000000 %
b1101000000000000000000 3
b1101000000000000000000 5
b1000010 -
b10100101 *
1)
#330
0)
#331
b1 &
b1 1
b1000011 -
b10100110 *
b10 6
b1101000000000000000001 %
b1101000000000000000001 3
b1101000000000000000001 5
1)
#332
0)
#333
b10 &
b10 1
b11 6
b1101000000000000000010 %
b1101000000000000000010 3
b1101000000000000000010 5
b1000100 -
b10100111 *
1)
#334
0)
#335
b11 &
b11 1
b1000101 -
b10101000 *
b100 6
b1101000000000000000011 %
b1101000000000000000011 3
b1101000000000000000011 5
1)
#336
0)
#337
0'
b0 6
b1101000000000000000000 0
b1000110 -
b10101001 *
1)
#338
0)
#339
b1100100 (
b10101010 *
b1100100 +
1)
#340
0)
#341
b10000 ,
bx $
bx .
b11110000000000000000000000000000 0
b1101 2
b1101 9
1'
b1101 8
b110100 "
b110100 /
b110100 7
b1100101 (
b10101011 *
b1100101 +
1)
#342
0)
#343
b110100 &
b110100 1
b1000111 -
b10101100 *
b1 6
b110100 %
b110100 3
b110100 5
1)
#344
0)
#345
b110101 &
b110101 1
b10 6
b110101 %
b110101 3
b110101 5
bx0000000000110100 $
bx0000000000110100 .
b1001000 -
b10101101 *
1)
#346
0)
#347
b110110 &
b110110 1
b1001001 -
b10101110 *
b11 6
b110110 %
b110110 3
b110110 5
bx00000000001101010000000000110100 $
bx00000000001101010000000000110100 .
1)
#348
0)
#349
b110111 &
b110111 1
b100 6
b110111 %
b110111 3
b110111 5
bx000000000011011000000000001101010000000000110100 $
bx000000000011011000000000001101010000000000110100 .
b1001010 -
b10101111 *
1)
#350
0)
#351
0'
b1001011 -
b10110000 *
b0 6
b110100 0
b110111000000000011011000000000001101010000000000110100 $
b110111000000000011011000000000001101010000000000110100 .
1)
#352
0)
#353
b1100110 (
b10110001 *
b1100110 +
1)
#354
0)
#355
b10001 ,
b1100111000000000110011000000000011001010000000001100100 $
b1100111000000000110011000000000011001010000000001100100 .
b1100100 0
b11001 2
b11001 9
0'
b11001 8
b1100101 "
b1100101 /
b1100101 7
b1100111 (
b10110010 *
b1100111 +
1)
#356
0)
#357
b1101000 (
b10110011 *
b1101000 +
1)
#358
0)
#359
b1100110 "
b1100110 /
b1100110 7
b1101001 (
b10110100 *
b1101001 +
1)
#360
0)
#361
b1101010 (
b10110101 *
b1101010 +
1)
#362
0)
#363
b1100111 "
b1100111 /
b1100111 7
b1101011 (
b10110110 *
b1101011 +
1)
#364
0)
#365
b1101100 (
b10110111 *
b1101100 +
1)
#366
0)
#367
b1101101 (
b10111000 *
b1101101 +
1)
#368
0)
#369
b1101110 (
b10111001 *
b1101110 +
1)
#370
0)
#371
b10010 ,
b11000000000000001000000000000000010000000000000000 $
b11000000000000001000000000000000010000000000000000 .
b1101000000000000000000 0
b0 2
b0 9
1'
b110000000000000000 8
b11000000000000000000 "
b11000000000000000000 /
b11000000000000000000 7
b1101111 (
b10111010 *
b1101111 +
1)
#372
0)
#373
b0 &
b0 1
b1 6
b11000000000000000000 %
b11000000000000000000 3
b11000000000000000000 5
b1001100 -
b10111011 *
1)
#374
0)
#375
b1 &
b1 1
b1001101 -
b10111100 *
b10 6
b11000000000000000001 %
b11000000000000000001 3
b11000000000000000001 5
1)
#376
0)
#377
b10 &
b10 1
b11 6
b11000000000000000010 %
b11000000000000000010 3
b11000000000000000010 5
b1001110 -
b10111101 *
1)
#378
0)
#379
b11 &
b11 1
b1001111 -
b10111110 *
b100 6
b11000000000000000011 %
b11000000000000000011 3
b11000000000000000011 5
1)
#380
0)
#381
0'
b0 6
b11000000000000000000 0
b1010000 -
b10111111 *
1)
#382
0)
#383
b1110000 (
b11000000 *
b1110000 +
1)
#384
0)
