old/ALU.v
//An ALU module for the integer pipeline.
//List of ops accepted:
//0: NOP
//1: ADD
//2: ADDC
//3: SUB
//4: SUBC
//5: BSL
//6: BSR
//7: AND
//8: OR
//9: INV
//10: XOR
module ALU(
  OP,
  FLGIN,
  A,
  B,
  flgOut,
  out,
  shouldWriteBack
  );

input [3:0] OP;
input [7:0] FLGIN;
input [15:0] A;
input [15:0] B;
output [7:0] flgOut;
output [15:0] out;
output shouldWriteBack;

wire [15:0] nopWire;
wire [16:0] addWire;
wire [16:0] addcWire;
wire [15:0] subWire;
wire [15:0] subcWire;
wire [15:0] bslWire;
wire [15:0] bsrWire;
wire [15:0] andWire;
wire [15:0] orWire;
wire [15:0] invWire;
wire [15:0] xorWire;

wire [15:0] outputMuxWire[15:0];

//Assign the wires to their respective actions:
assign nopWire=0;
assign addWire=A+B;
assign addcWire=A+B+FLGIN[1];
assign subWire=A-B;
assign subcWire=A-B-FLGIN[1];
assign bslWire=A<<B;
assign bsrWire=A>>B;
assign andWire=A&B;
assign orWire=A|B;
assign invWire=~A;
assign xorWire=A^B;

assign outputMuxWire[0]=nopWire;
assign outputMuxWire[1]=addWire[15:0];
assign outputMuxWire[2]=addcWire[15:0];
assign outputMuxWire[3]=subWire;
assign outputMuxWire[4]=subcWire;
assign outputMuxWire[5]=bslWire;
assign outputMuxWire[6]=bsrWire;
assign outputMuxWire[7]=andWire;
assign outputMuxWire[8]=orWire;
assign outputMuxWire[9]=invWire;
assign outputMuxWire[10]=xorWire;
assign outputMuxWire[11]=nopWire;
assign outputMuxWire[12]=nopWire;
assign outputMuxWire[13]=nopWire;
assign outputMuxWire[14]=nopWire;
assign outputMuxWire[15]=nopWire;

//Set normal computation outputs.
assign out=outputMuxWire[OP];
assign shouldWriteBack=OP>0&&OP<11; //Enables NOPs.

//Now construct flags: (zero, carry, overflow, negative)
wire zero, carry, overflow, negative;

wire zeroMuxWire[10:0];
assign zeroMuxWire[0]=nopWire==0;
assign zeroMuxWire[1]=addWire==0;
assign zeroMuxWire[2]=addcWire==0;
assign zeroMuxWire[3]=subWire==0;
assign zeroMuxWire[4]=subcWire==0;
assign zeroMuxWire[5]=bslWire==0;
assign zeroMuxWire[6]=bsrWire==0;
assign zeroMuxWire[7]=andWire==0;
assign zeroMuxWire[8]=orWire==0;
assign zeroMuxWire[9]=invWire==0;
assign zeroMuxWire[10]=xorWire==0;

assign zero=zeroMuxWire[OP];

assign carry=addWire[16]&&(OP==1)||addcWire[16]&&(OP==2);

//I'll figure out overflow later on:
assign overflow=0;
//Negative:
assign negative=subWire<0&&(OP==3)||subcWire<0&&(OP==4);

//Condense all of the flags:
assign flgOut[0]=zero;
assign flgOut[1]=carry;
assign flgOut[2]=overflow;
assign flgOut[3]=negative;
assign flgOut[7:4]=0;

endmodule

RevisionB/intpipe.v
//Defines an integer pipeline that can attempt to do internal dependency resolution.
//By shifting execution to individual components, the revision B core
//should be easier to debug.

module intpipe(op, clk, rst, opWt, regWt, aSel, bSel, cSel, aDat, bDat, flgIn, FLGWRI, COUT, CWRI, AS, BS, CS, FLGOUT);

input [3:0] op;
input clk;
input rst;
//Wait signals for operations and the register file.
input opWt;
input regWt;
input [2:0] aSel;
input [2:0] bSel;
input [2:0] cSel;
input [15:0] aDat;
input [15:0] bDat;
input [7:0] flgIn;
output [15:0] COUT;
output [2:0] AS;
output [2:0] BS;
output [2:0] CS;
output CWRI; 
output FLGWRI;
output [7:0] FLGOUT;

assign AS=aSel;
assign BS=bSel;

//Now create some internal signals/shifters:
reg [3:0] opShifter[2:0]; //Fetch/data resolve, execute, writeback.
reg [2:0] destShifter[2:0]; //So that we can keep track of where each op wants to write.
reg [15:0] operandA;
reg [15:0] operandB;
reg [15:0] operandC;
reg cwr;

wire [2:0] dest0;
wire [2:0] dest1;
wire [2:0] dest2;
assign dest0=destShifter[0];
assign dest1=destShifter[1];
assign dest2=destShifter[2];

assign CS=destShifter[2];
assign CWRI=cwr;

wire [15:0] aluOut;
wire [7:0] flgs;
wire aluWriteback;
reg [7:0] curFlgs;
assign COUT=aluOut;

wire [3:0] curOp;
assign curOp=opShifter[1];

//wire [15:0] aluA [0:1];
//wire [15:0] aluB [0:1];
//assign aluA[0]=operandA;
//assign aluB[0]=operandB;
//assign aluA[1]=operandC;
//assign aluB[1]=operandC;

wire aluASelect;
wire aluBSelect;

assign aluASelect=(aSel==destShifter[1]);//||(aSel==destShifter[1]);
assign aluBSelect=(bSel==destShifter[1]);//||(bSel==destShifter[1]);

//This is so that ALU data can be checked:
//wire [15:0] a;
//wire [15:0] b;

//assign a=aluA[aluASelect];
//assign b=aluB[aluBSelect];

ALU crunchinator(opShifter[1], curFlgs, operandA, operandB, flgs, aluOut, aluWriteback);

always@(posedge clk) begin
	//First, check whether we should shift:
	if(~opWt&&~regWt) begin //TODO: consider converting to inverted or.
		opShifter[0]<=op;
		opShifter[1]<=opShifter[0];
		opShifter[2]<=opShifter[1];

		destShifter[0]<=cSel;
		destShifter[1]<=destShifter[0];
		destShifter[2]<=destShifter[1];
	end

	//Now do some general stuff:
	cwr<=aluWriteback;

	//operandA<=aDat;
	//operandB<=bDat;
	operandC<=aluOut;

	if(aluASelect) begin //aSel==destShifter[1]) begin
		operandA<=aluOut;
	end

	//This must be exclusive with the above.
	//else if(aSel==destShifter[1]) begin
	//	operandA<=operandC;
	//end

	else begin
		operandA<=aDat;
	end

	if(aluBSelect) begin//bSel==destShifter[1]) begin
		operandB<=aluOut;
	end

	//else if(bSel==destShifter[1]) begin
	//	operandB<=operandC;
	//end

	else begin
		operandB<=bDat;
	end
	//There need not be anything to handle writebacks if there's a stall, because the pipe
	//will simply freeze.
end

initial begin
	destShifter[0]=0;
	destShifter[1]=0;
	destShifter[2]=0;
end
endmodule

RevisionB/intpipe_tb.v
//This is a testbench for the integer pipeline.
//It for-loops its way through all possible operations and tests various combinations of operands.
//If any disparities in actions are detected, it makes note of that.
module intpipe_tb();

reg [3:0] opList[0:255];
reg [2:0] aSelList[0:255];
reg [2:0] bSelList[0:255];
reg [2:0] cSelList[0:255];
reg clk;
reg [31:0] incr;

wire rst, opWt, regWt;
wire [15:0] aDat;
wire [15:0] bDat;
wire [7:0] flgIn;

wire FLGWRI;
wire [15:0] COUT;
wire CWRI;
wire [2:0] AS;
wire [2:0] BS;
wire [2:0] CS;
wire [7:0] FLGOUT;

assign rst=0;
assign opWt=0;
assign regWt=0;
assign aDat=2;
assign bDat=3;
assign flgIn=0;

intpipe ipipe(opList[incr], clk, rst, opWt, regWt, aSelList[incr], bSelList[incr], cSelList[incr], aDat, bDat, flgIn, FLGWRI, COUT, CWRI, AS, BS, CS, FLGOUT);

//Now generate some constructs for validation:
reg [15:0] answers[0:255];
reg [3:0] curOp;
wire [15:0] A;
wire [15:0] B;
wire [15:0] C;
wire [7:0] aluFlgOut;
wire aluWriteback;
reg [15:0] virtualRegFile [0:7];

assign A=2;
assign B=3;
wire [3:0] aluOp;
assign aluOp=opList[incr-2];
//ALU cruncher(curOp, flgIn, A, B, aluFlgOut, C, aluWriteback);
ALU aluinator(opList[incr-2], flgIn, A, B, aluFlgOut, C, aluWriteBack);
   
reg startChecks;

wire correct;
reg [31:0] correctCount;
assign correct=C==COUT;

initial begin
	for(incr=0;incr<256;incr=incr+1) begin
		//opList[incr]=incr%16;
		opList[incr]=1; //Just add to make life easier.
		aSelList[incr]=1;//incr%2+1;
		bSelList[incr]=3;//incr%4;
		cSelList[incr]=3'b010; //This should force the pipeline to occasionally do bypass.
	end

	//Set up a quick fixed list to check for pipeline coherency:
	aSelList[1]=2;
	bSelList[2]=2;
	aSelList[4]=2;
	aSelList[6]=2;
	aSelList[8]=2;
	aSelList[9]=2;

	//Now compute results:
	//for(incr=0;incr<256;incr=incr+1) begin
	//	curOp=answers[incr];
	//	//A=virtualRegFile[aSelList[incr]];
	//	//B=virtualRegFile[bSelList[incr]];
	//	answers[incr]=C;
	//	virtualRegFile[cSelList[incr]]=C;
	//end

	clk=0;
	incr=0;
	correctCount=0;
end

always begin
	#1 clk=~clk;
end

initial begin
	#530 $finish;
end

always@(posedge clk) begin
	incr=incr+1;
	if(correct) begin
		correctCount=correctCount+1;
	end
end

initial begin
	$dumpfile("intpipe_tb.vcd");
	$dumpvars;
end
endmodule

RevisionB/intpipe_tb.vcd
$date
	Tue Dec 29 19:46:49 2015
$end
$version
	Icarus Verilog
$end
$timescale
	1s
$end
$scope module intpipe_tb $end
$var wire 16 ! A [15:0] $end
$var wire 16 " B [15:0] $end
$var wire 8 # FLGOUT [7:0] $end
$var wire 1 $ FLGWRI $end
$var wire 16 % aDat [15:0] $end
$var wire 4 & aluOp [3:0] $end
$var wire 16 ' bDat [15:0] $end
$var wire 8 ( flgIn [7:0] $end
$var wire 1 ) opWt $end
$var wire 1 * regWt $end
$var wire 1 + rst $end
$var wire 1 , correct $end
$var wire 1 - aluWriteBack $end
$var wire 8 . aluFlgOut [7:0] $end
$var wire 1 / CWRI $end
$var wire 3 0 CS [2:0] $end
$var wire 16 1 COUT [15:0] $end
$var wire 16 2 C [15:0] $end
$var wire 3 3 BS [2:0] $end
$var wire 3 4 AS [2:0] $end
$var reg 1 5 clk $end
$var reg 32 6 correctCount [31:0] $end
$var reg 32 7 incr [31:0] $end
$scope module aluinator $end
$var wire 16 8 A [15:0] $end
$var wire 16 9 B [15:0] $end
$var wire 8 : FLGIN [7:0] $end
$var wire 4 ; OP [3:0] $end
$var wire 16 < andWire [15:0] $end
$var wire 1 = carry $end
$var wire 16 > invWire [15:0] $end
$var wire 1 ? negative $end
$var wire 16 @ nopWire [15:0] $end
$var wire 16 A orWire [15:0] $end
$var wire 16 B out [15:0] $end
$var wire 1 C overflow $end
$var wire 1 - shouldWriteBack $end
$var wire 16 D xorWire [15:0] $end
$var wire 1 E zero $end
$var wire 16 F subcWire [15:0] $end
$var wire 16 G subWire [15:0] $end
$var wire 8 H flgOut [7:0] $end
$var wire 16 I bsrWire [15:0] $end
$var wire 16 J bslWire [15:0] $end
$var wire 17 K addcWire [16:0] $end
$var wire 17 L addWire [16:0] $end
$upscope $end
$scope module ipipe $end
$var wire 3 M AS [2:0] $end
$var wire 3 N BS [2:0] $end
$var wire 16 O COUT [15:0] $end
$var wire 3 P CS [2:0] $end
$var wire 1 / CWRI $end
$var wire 8 Q FLGOUT [7:0] $end
$var wire 1 $ FLGWRI $end
$var wire 16 R aDat [15:0] $end
$var wire 3 S aSel [2:0] $end
$var wire 16 T bDat [15:0] $end
$var wire 3 U bSel [2:0] $end
$var wire 3 V cSel [2:0] $end
$var wire 1 5 clk $end
$var wire 4 W curOp [3:0] $end
$var wire 3 X dest0 [2:0] $end
$var wire 3 Y dest1 [2:0] $end
$var wire 3 Z dest2 [2:0] $end
$var wire 8 [ flgIn [7:0] $end
$var wire 4 \ op [3:0] $end
$var wire 1 ) opWt $end
$var wire 1 * regWt $end
$var wire 1 + rst $end
$var wire 8 ] flgs [7:0] $end
$var wire 1 ^ aluWriteback $end
$var wire 16 _ aluOut [15:0] $end
$var wire 1 ` aluBSelect $end
$var wire 1 a aluASelect $end
$var reg 8 b curFlgs [7:0] $end
$var reg 1 c cwr $end
$var reg 16 d operandA [15:0] $end
$var reg 16 e operandB [15:0] $end
$var reg 16 f operandC [15:0] $end
$scope module crunchinator $end
$var wire 16 g A [15:0] $end
$var wire 16 h B [15:0] $end
$var wire 8 i FLGIN [7:0] $end
$var wire 4 j OP [3:0] $end
$var wire 16 k andWire [15:0] $end
$var wire 1 l carry $end
$var wire 16 m invWire [15:0] $end
$var wire 1 n negative $end
$var wire 16 o nopWire [15:0] $end
$var wire 16 p orWire [15:0] $end
$var wire 16 q out [15:0] $end
$var wire 1 r overflow $end
$var wire 1 ^ shouldWriteBack $end
$var wire 16 s xorWire [15:0] $end
$var wire 1 t zero $end
$var wire 16 u subcWire [15:0] $end
$var wire 16 v subWire [15:0] $end
$var wire 8 w flgOut [7:0] $end
$var wire 16 x bsrWire [15:0] $end
$var wire 16 y bslWire [15:0] $end
$var wire 17 z addcWire [16:0] $end
$var wire 17 { addWire [16:0] $end
$upscope $end
$upscope $end
$upscope $end
$enddefinitions $end
#0
$dumpvars
bx {
bx z
bx y
bx x
b0x0xx w
bx v
bx u
xt
bx s
0r
bx q
bx p
b0 o
xn
bx m
xl
bx k
bx j
bx i
bx h
bx g
bx f
bx e
bx d
xc
bx b
0a
0`
bx _
x^
b0x0xx ]
b1 \
b0 [
b0 Z
b0 Y
b0 X
bx W
b10 V
b11 U
b11 T
b1 S
b10 R
bz Q
b0 P
bx O
b11 N
b1 M
b101 L
b101 K
b10000 J
b0 I
b0x H
b1111111111111111 G
b1111111111111111 F
xE
b1 D
0C
bx B
b11 A
b0 @
0?
b1111111111111101 >
0=
b10 <
bx ;
b0 :
b11 9
b10 8
b0 7
b0 6
05
b1 4
b11 3
bx 2
bx 1
b0 0
x/
b0x .
x-
x,
0+
0*
0)
b0 (
b11 '
bx &
b10 %
z$
bz #
b11 "
b10 !
$end
#1
b10 k
b11 p
b1111111111111101 m
b1 s
b101 {
b1111111111111111 v
b10000 y
b0 x
b11 e
b11 h
b10 d
b10 g
b10 X
b10 4
b10 M
b10 S
b1 7
15
#2
05
#3
0l
0n
1^
b10 Y
1`
b1 W
1,
b101 1
b101 O
b101 _
b101 q
b0 ]
b0 w
0t
b1 j
1-
b1 4
b1 M
b1 S
b10 3
b10 N
b10 U
b1 &
b101 2
b101 B
b0 .
b0 H
0E
b1 ;
b10 7
15
#4
05
#5
b101 f
1/
1c
b10 Z
b10 0
b10 P
b1 6
b11 3
b11 N
0`
b11 U
b11 7
15
#6
05
#7
b10 6
b10 4
b10 M
1a
b10 S
b100 7
15
#8
05
#9
b11 6
b1 4
b1 M
0a
b1 S
b101 7
15
#10
05
#11
b100 6
b10 4
b10 M
1a
b10 S
b110 7
15
#12
05
#13
b101 6
b1 4
b1 M
0a
b1 S
b111 7
15
#14
05
#15
b110 6
b10 4
b10 M
1a
b10 S
b1000 7
15
#16
05
#17
b1 k
b111 p
b1111111111111010 m
b110 s
0,
b1000 1
b1000 O
b1000 _
b1000 q
b1000 {
b10 v
b101000 y
b101 d
b101 g
b111 6
b1001 7
15
#18
05
#19
b0 k
b1011 p
b1111111111110111 m
b1011 s
b1011 1
b1011 O
b1011 _
b1011 q
b1011 {
b101 v
b1000000 y
b1 x
b1000 d
b1000 g
b1000 f
b1 4
b1 M
0a
b1 S
b1010 7
15
#20
05
#21
b10 k
b11 p
b1111111111111101 m
b1 s
1,
b101 1
b101 O
b101 _
b101 q
b101 {
b1111111111111111 v
b10000 y
b0 x
b10 d
b10 g
b1011 f
b1011 7
15
#22
05
#23
b101 f
b1000 6
b1100 7
15
#24
05
#25
b1001 6
b1101 7
15
#26
05
#27
b1010 6
b1110 7
15
#28
05
#29
b1011 6
b1111 7
15
#30
05
#31
b1100 6
b10000 7
15
#32
05
#33
b1101 6
b10001 7
15
#34
05
#35
b1110 6
b10010 7
15
#36
05
#37
b1111 6
b10011 7
15
#38
05
#39
b10000 6
b10100 7
15
#40
05
#41
b10001 6
b10101 7
15
#42
05
#43
b10010 6
b10110 7
15
#44
05
#45
b10011 6
b10111 7
15
#46
05
#47
b10100 6
b11000 7
15
#48
05
#49
b10101 6
b11001 7
15
#50
05
#51
b10110 6
b11010 7
15
#52
05
#53
b10111 6
b11011 7
15
#54
05
#55
b11000 6
b11100 7
15
#56
05
#57
b11001 6
b11101 7
15
#58
05
#59
b11010 6
b11110 7
15
#60
05
#61
b11011 6
b11111 7
15
#62
05
#63
b11100 6
b100000 7
15
#64
05
#65
b11101 6
b100001 7
15
#66
05
#67
b11110 6
b100010 7
15
#68
05
#69
b11111 6
b100011 7
15
#70
05
#71
b100000 6
b100100 7
15
#72
05
#73
b100001 6
b100101 7
15
#74
05
#75
b100010 6
b100110 7
15
#76
05
#77
b100011 6
b100111 7
15
#78
05
#79
b100100 6
b101000 7
15
#80
05
#81
b100101 6
b101001 7
15
#82
05
#83
b100110 6
b101010 7
15
#84
05
#85
b100111 6
b101011 7
15
#86
05
#87
b101000 6
b101100 7
15
#88
05
#89
b101001 6
b101101 7
15
#90
05
#91
b101010 6
b101110 7
15
#92
05
#93
b101011 6
b101111 7
15
#94
05
#95
b101100 6
b110000 7
15
#96
05
#97
b101101 6
b110001 7
15
#98
05
#99
b101110 6
b110010 7
15
#100
05
#101
b101111 6
b110011 7
15
#102
05
#103
b110000 6
b110100 7
15
#104
05
#105
b110001 6
b110101 7
15
#106
05
#107
b110010 6
b110110 7
15
#108
05
#109
b110011 6
b110111 7
15
#110
05
#111
b110100 6
b111000 7
15
#112
05
#113
b110101 6
b111001 7
15
#114
05
#115
b110110 6
b111010 7
15
#116
05
#117
b110111 6
b111011 7
15
#118
05
#119
b111000 6
b111100 7
15
#120
05
#121
b111001 6
b111101 7
15
#122
05
#123
b111010 6
b111110 7
15
#124
05
#125
b111011 6
b111111 7
15
#126
05
#127
b111100 6
b1000000 7
15
#128
05
#129
b111101 6
b1000001 7
15
#130
05
#131
b111110 6
b1000010 7
15
#132
05
#133
b111111 6
b1000011 7
15
#134
05
#135
b1000000 6
b1000100 7
15
#136
05
#137
b1000001 6
b1000101 7
15
#138
05
#139
b1000010 6
b1000110 7
15
#140
05
#141
b1000011 6
b1000111 7
15
#142
05
#143
b1000100 6
b1001000 7
15
#144
05
#145
b1000101 6
b1001001 7
15
#146
05
#147
b1000110 6
b1001010 7
15
#148
05
#149
b1000111 6
b1001011 7
15
#150
05
#151
b1001000 6
b1001100 7
15
#152
05
#153
b1001001 6
b1001101 7
15
#154
05
#155
b1001010 6
b1001110 7
15
#156
05
#157
b1001011 6
b1001111 7
15
#158
05
#159
b1001100 6
b1010000 7
15
#160
05
#161
b1001101 6
b1010001 7
15
#162
05
#163
b1001110 6
b1010010 7
15
#164
05
#165
b1001111 6
b1010011 7
15
#166
05
#167
b1010000 6
b1010100 7
15
#168
05
#169
b1010001 6
b1010101 7
15
#170
05
#171
b1010010 6
b1010110 7
15
#172
05
#173
b1010011 6
b1010111 7
15
#174
05
#175
b1010100 6
b1011000 7
15
#176
05
#177
b1010101 6
b1011001 7
15
#178
05
#179
b1010110 6
b1011010 7
15
#180
05
#181
b1010111 6
b1011011 7
15
#182
05
#183
b1011000 6
b1011100 7
15
#184
05
#185
b1011001 6
b1011101 7
15
#186
05
#187
b1011010 6
b1011110 7
15
#188
05
#189
b1011011 6
b1011111 7
15
#190
05
#191
b1011100 6
b1100000 7
15
#192
05
#193
b1011101 6
b1100001 7
15
#194
05
#195
b1011110 6
b1100010 7
15
#196
05
#197
b1011111 6
b1100011 7
15
#198
05
#199
b1100000 6
b1100100 7
15
#200
05
#201
b1100001 6
b1100101 7
15
#202
05
#203
b1100010 6
b1100110 7
15
#204
05
#205
b1100011 6
b1100111 7
15
#206
05
#207
b1100100 6
b1101000 7
15
#208
05
#209
b1100101 6
b1101001 7
15
#210
05
#211
b1100110 6
b1101010 7
15
#212
05
#213
b1100111 6
b1101011 7
15
#214
05
#215
b1101000 6
b1101100 7
15
#216
05
#217
b1101001 6
b1101101 7
15
#218
05
#219
b1101010 6
b1101110 7
15
#220
05
#221
b1101011 6
b1101111 7
15
#222
05
#223
b1101100 6
b1110000 7
15
#224
05
#225
b1101101 6
b1110001 7
15
#226
05
#227
b1101110 6
b1110010 7
15
#228
05
#229
b1101111 6
b1110011 7
15
#230
05
#231
b1110000 6
b1110100 7
15
#232
05
#233
b1110001 6
b1110101 7
15
#234
05
#235
b1110010 6
b1110110 7
15
#236
05
#237
b1110011 6
b1110111 7
15
#238
05
#239
b1110100 6
b1111000 7
15
#240
05
#241
b1110101 6
b1111001 7
15
#242
05
#243
b1110110 6
b1111010 7
15
#244
05
#245
b1110111 6
b1111011 7
15
#246
05
#247
b1111000 6
b1111100 7
15
#248
05
#249
b1111001 6
b1111101 7
15
#250
05
#251
b1111010 6
b1111110 7
15
#252
05
#253
b1111011 6
b1111111 7
15
#254
05
#255
b1111100 6
b10000000 7
15
#256
05
#257
b1111101 6
b10000001 7
15
#258
05
#259
b1111110 6
b10000010 7
15
#260
05
#261
b1111111 6
b10000011 7
15
#262
05
#263
b10000000 6
b10000100 7
15
#264
05
#265
b10000001 6
b10000101 7
15
#266
05
#267
b10000010 6
b10000110 7
15
#268
05
#269
b10000011 6
b10000111 7
15
#270
05
#271
b10000100 6
b10001000 7
15
#272
05
#273
b10000101 6
b10001001 7
15
#274
05
#275
b10000110 6
b10001010 7
15
#276
05
#277
b10000111 6
b10001011 7
15
#278
05
#279
b10001000 6
b10001100 7
15
#280
05
#281
b10001001 6
b10001101 7
15
#282
05
#283
b10001010 6
b10001110 7
15
#284
05
#285
b10001011 6
b10001111 7
15
#286
05
#287
b10001100 6
b10010000 7
15
#288
05
#289
b10001101 6
b10010001 7
15
#290
05
#291
b10001110 6
b10010010 7
15
#292
05
#293
b10001111 6
b10010011 7
15
#294
05
#295
b10010000 6
b10010100 7
15
#296
05
#297
b10010001 6
b10010101 7
15
#298
05
#299
b10010010 6
b10010110 7
15
#300
05
#301
b10010011 6
b10010111 7
15
#302
05
#303
b10010100 6
b10011000 7
15
#304
05
#305
b10010101 6
b10011001 7
15
#306
05
#307
b10010110 6
b10011010 7
15
#308
05
#309
b10010111 6
b10011011 7
15
#310
05
#311
b10011000 6
b10011100 7
15
#312
05
#313
b10011001 6
b10011101 7
15
#314
05
#315
b10011010 6
b10011110 7
15
#316
05
#317
b10011011 6
b10011111 7
15
#318
05
#319
b10011100 6
b10100000 7
15
#320
05
#321
b10011101 6
b10100001 7
15
#322
05
#323
b10011110 6
b10100010 7
15
#324
05
#325
b10011111 6
b10100011 7
15
#326
05
#327
b10100000 6
b10100100 7
15
#328
05
#329
b10100001 6
b10100101 7
15
#330
05
#331
b10100010 6
b10100110 7
15
#332
05
#333
b10100011 6
b10100111 7
15
#334
05
#335
b10100100 6
b10101000 7
15
#336
05
#337
b10100101 6
b10101001 7
15
#338
05
#339
b10100110 6
b10101010 7
15
#340
05
#341
b10100111 6
b10101011 7
15
#342
05
#343
b10101000 6
b10101100 7
15
#344
05
#345
b10101001 6
b10101101 7
15
#346
05
#347
b10101010 6
b10101110 7
15
#348
05
#349
b10101011 6
b10101111 7
15
#350
05
#351
b10101100 6
b10110000 7
15
#352
05
#353
b10101101 6
b10110001 7
15
#354
05
#355
b10101110 6
b10110010 7
15
#356
05
#357
b10101111 6
b10110011 7
15
#358
05
#359
b10110000 6
b10110100 7
15
#360
05
#361
b10110001 6
b10110101 7
15
#362
05
#363
b10110010 6
b10110110 7
15
#364
05
#365
b10110011 6
b10110111 7
15
#366
05
#367
b10110100 6
b10111000 7
15
#368
05
#369
b10110101 6
b10111001 7
15
#370
05
#371
b10110110 6
b10111010 7
15
#372
05
#373
b10110111 6
b10111011 7
15
#374
05
#375
b10111000 6
b10111100 7
15
#376
05
#377
b10111001 6
b10111101 7
15
#378
05
#379
b10111010 6
b10111110 7
15
#380
05
#381
b10111011 6
b10111111 7
15
#382
05
#383
b10111100 6
b11000000 7
15
#384
05
#385
b10111101 6
b11000001 7
15
#386
05
#387
b10111110 6
b11000010 7
15
#388
05
#389
b10111111 6
b11000011 7
15
#390
05
#391
b11000000 6
b11000100 7
15
#392
05
#393
b11000001 6
b11000101 7
15
#394
05
#395
b11000010 6
b11000110 7
15
#396
05
#397
b11000011 6
b11000111 7
15
#398
05
#399
b11000100 6
b11001000 7
15
#400
05
#401
b11000101 6
b11001001 7
15
#402
05
#403
b11000110 6
b11001010 7
15
#404
05
#405
b11000111 6
b11001011 7
15
#406
05
#407
b11001000 6
b11001100 7
15
#408
05
#409
b11001001 6
b11001101 7
15
#410
05
#411
b11001010 6
b11001110 7
15
#412
05
#413
b11001011 6
b11001111 7
15
#414
05
#415
b11001100 6
b11010000 7
15
#416
05
#417
b11001101 6
b11010001 7
15
#418
05
#419
b11001110 6
b11010010 7
15
#420
05
#421
b11001111 6
b11010011 7
15
#422
05
#423
b11010000 6
b11010100 7
15
#424
05
#425
b11010001 6
b11010101 7
15
#426
05
#427
b11010010 6
b11010110 7
15
#428
05
#429
b11010011 6
b11010111 7
15
#430
05
#431
b11010100 6
b11011000 7
15
#432
05
#433
b11010101 6
b11011001 7
15
#434
05
#435
b11010110 6
b11011010 7
15
#436
05
#437
b11010111 6
b11011011 7
15
#438
05
#439
b11011000 6
b11011100 7
15
#440
05
#441
b11011001 6
b11011101 7
15
#442
05
#443
b11011010 6
b11011110 7
15
#444
05
#445
b11011011 6
b11011111 7
15
#446
05
#447
b11011100 6
b11100000 7
15
#448
05
#449
b11011101 6
b11100001 7
15
#450
05
#451
b11011110 6
b11100010 7
15
#452
05
#453
b11011111 6
b11100011 7
15
#454
05
#455
b11100000 6
b11100100 7
15
#456
05
#457
b11100001 6
b11100101 7
15
#458
05
#459
b11100010 6
b11100110 7
15
#460
05
#461
b11100011 6
b11100111 7
15
#462
05
#463
b11100100 6
b11101000 7
15
#464
05
#465
b11100101 6
b11101001 7
15
#466
05
#467
b11100110 6
b11101010 7
15
#468
05
#469
b11100111 6
b11101011 7
15
#470
05
#471
b11101000 6
b11101100 7
15
#472
05
#473
b11101001 6
b11101101 7
15
#474
05
#475
b11101010 6
b11101110 7
15
#476
05
#477
b11101011 6
b11101111 7
15
#478
05
#479
b11101100 6
b11110000 7
15
#480
05
#481
b11101101 6
b11110001 7
15
#482
05
#483
b11101110 6
b11110010 7
15
#484
05
#485
b11101111 6
b11110011 7
15
#486
05
#487
b11110000 6
b11110100 7
15
#488
05
#489
b11110001 6
b11110101 7
15
#490
05
#491
b11110010 6
b11110110 7
15
#492
05
#493
b11110011 6
b11110111 7
15
#494
05
#495
b11110100 6
b11111000 7
15
#496
05
#497
b11110101 6
b11111001 7
15
#498
05
#499
b11110110 6
b11111010 7
15
#500
05
#501
b11110111 6
b11111011 7
15
#502
05
#503
b11111000 6
b11111100 7
15
#504
05
#505
b11111001 6
b11111101 7
15
#506
05
#507
b11111010 6
b11111110 7
15
#508
05
#509
b11111011 6
b11111111 7
15
#510
05
#511
b11111100 6
bx \
bx 4
bx M
xa
bx S
bx 3
bx N
x`
bx U
bx V
b100000000 7
15
#512
05
#513
bx X
b11111101 6
b100000001 7
15
#514
05
#515
xl
xn
x^
bx Y
bx W
bx 1
bx O
bx _
bx q
b0x0xx ]
b0x0xx w
xt
bx j
x-
bx &
x,
bx 2
bx B
b0x .
b0x H
xE
bx ;
b100000010 7
15
#516
05
#517
bx f
x/
xc
bx Z
bx 0
bx P
b100000011 7
15
#518
05
#519
b100000100 7
15
#520
05
#521
b100000101 7
15
#522
05
#523
b100000110 7
15
#524
05
#525
b100000111 7
15
#526
05
#527
b100001000 7
15
#528
05
#529
b100001001 7
15
