RevisionB/comparator.v
//This defines a comparator for use with the 
//Branch-Memory Unit.
module comparator(
  A,
  B,
  greater,
  less,
  same
  );
  
input [15:0] A;
input [15:0] B;
output greater;
output less;
output same;

assign greater=A>B;
assign same=A==B;
assign less=~(greater||same); //Neither.
  
endmodule

optyper.v
//This unit determines the category of operation requested of the Branch/Memory Unit.
module optyper(
	OP,
	load,
	store,
	branch,
	cmp,
	stack,
	ldl//,
	//call
	);

input [6:0] OP;
output load;
output store;
output branch;
output cmp;
output stack;
output ldl;

assign ldl=(OP==64)||stack;
assign stack=(OP>39)&&(OP<47);
assign branch=(OP>50)&&(OP<55);
assign load=(OP==60)||(OP==43);
assign store=(OP==61)||(OP==42);
assign cmp=(OP==50);

endmodule

old/pointer.v
//Represents a pointer that can be incremented, decremented,
//or written to. This will be used for both the program counter
//and stack register.
module pointer(
	CLK,
	INCREMENT,
	DECREMENT,
	NEWV,
	WRITE,
	out
	);

input CLK;
input INCREMENT;
input DECREMENT;
input [31:0] NEWV;
input WRITE;
output [31:0] out;

reg [31:0] val;
assign out=val;

//By triggering on the negative edge, I'm effectively staggering RAM access and reads. 
//This may potentially possibly maybe allow me to push higher clockspeeds.
always@(negedge CLK) begin
	if(~WRITE&&INCREMENT) begin
		val<=val+1;
	end
	else if(~WRITE&&DECREMENT) begin
	  val<=val-1;
	end
	else if(WRITE) begin
		val<=NEWV;
	end
end

initial begin
	val=0;
end
endmodule

dispatchu.v
//Manages memory and 
//dispatches instructions to the rest of
//the processor.
//This unit doesn't have a proper pipeline,
//rather it is mostly hard-wired combinational logic.
module dispatchu(
  CLK,
  MEMDAT,
  ADAT,
  BDAT,
  CDAT,
  addr,
  memOut,
  memWrite,
  Cout,
  cWrite,
  Asel,
  Bsel,
  Csel,
  intPipeOp,
  intPipeA,
  intPipeB,
  intPipeC
  );
  
input CLK;
input [15:0] MEMDAT;
input [15:0] ADAT;
input [15:0] BDAT;
input [15:0] CDAT;
output [31:0] addr;
output [15:0] memOut;
output memWrite;
output [15:0] Cout;
output cWrite;
output [2:0] Asel;
output [2:0] Bsel;
output [2:0] Csel;
output [3:0] intPipeOp;
output [2:0] intPipeA;
output [2:0] intPipeB;
output [2:0] intPipeC;
  
reg stkpInc, stkpDec, stkpWrite;
wire [31:0] ABBus;
wire [31:0] stkPtrBus;
pointer stackPointer(CLK, stkpInc, stkpDec, ABBus, stkpWrite, stkPtrBus);

reg pcWrite;
wire pcInc, pcDec;
wire [31:0] PCBus;
wire [31:0] pcInputBus [1:0];
wire [31:0] extendedMemoryInputBus; //Allows for rets.
assign extendedMemoryInputBus[31:16]=0;
assign extendedMemoryInputBus[15:0]=MEMDAT;
assign pcInputBus[0]=ABBus;
assign pcInputBus[1]=extendedMemoryInputBus;
reg pcInputSel;
pointer programCounter(CLK, pcInc, pcDec, pcInputBus[pcInputSel], pcWrite, PCBus);

assign ABBus[31:16]=ADAT;
assign ABBus[15:0]=BDAT;

reg [15:0] memOutReg;
assign memOut=memOutReg;

wire [31:0] addrMux[0:2];
//Addressing can either be from:
//1. The program counter.
//2. The AB bus.
//3. The the stack pointer.
assign addrMux[0]=PCBus;
assign addrMux[1]=ABBus;
assign addrMux[2]=stkPtrBus;
reg [1:0] addrMuxSelector;
assign addr=addrMux[addrMuxSelector];

reg [15:0] curVals;
wire [6:0] op;
wire [2:0] a;
wire [2:0] b;
wire [2:0] c;
assign op=curVals[15:9];
assign a=curVals[8:6];
assign b=curVals[5:3];
assign c=curVals[2:0];
assign Asel=a;
assign Bsel=b;
assign Csel=c;
assign intPipeA=a;
assign intPipeB=b;
assign intPipeC=c;

wire [15:0] cOutMux[2:0];
reg [1:0] cSelector;
assign cOutMux[0]=MEMDAT;
assign cOutMux[1]=curVals[14:0];
assign cOutMux[2]=stkPtrBus[15:0];
assign Cout=cOutMux[cSelector];

//Assign out an optyper to get operation types:
wire load, store, branch, cmp, stack, ldl, call, intOp;
optyper ot(op, load, store, branch, cmp, stack, ldl);//, call);
assign intOp=(~load)&&(~store)&&(~branch)&&(~cmp)&&(~stack)&&(~ldl);
//assign cWrite=ldl||(some representative combinational logic.

wire [3:0] intPipeOpSelector[3:0];
assign intPipeOpSelector[0]=0;
assign intPipeOpSelector[1]=op[3:0];
assign intPipeOp=intPipeOpSelector[intOp];

wire fetchNextOp;
assign fetchNextOp=intOp;
//assign pcInc=fetchNextOp;

//Build a comparator so that we can have flags.
wire greater, less, same;
comparator comp(ADAT, BDAT, greater, less, same);

reg gFlag, lFlag, sFlag;

reg memWriteReg;
assign memWrite=memWriteReg;

reg stateReg;
reg cWriteReg;
assign cWrite=cWriteReg;
assign pcInc=~stateReg&&fetchNextOp;
assign pcDec=0;

//This 1-state design is going to be the biggest bottleneck
//to reaching higher clockspeeds.
always@(posedge CLK) begin
  if(stateReg) begin //Second state for actions that require another state.
    stateReg<=1'b0;
    //curVals<=0; //Reset the current thingy.
    addrMuxSelector<=0;
    
    if(op!=44&&op!=45) begin
      curVals<=0; //Reset the current instruction to NOP.
    end
    
    if(op==44) begin //Second half of call; completes the jump.
      
    end
    
    else if(op==45) begin //Second half of ret; completes the jump.
      pcWrite<=0;
    end
    
    else if(stack) begin //Be sure to do the stack register stuff:
      if(store) begin
	memWriteReg<=0;
	stkpDec<=0;
      end
      else begin
	stkpInc<=0;
	cWriteReg<=1;
      end
    end
    
    else if(~stack) begin
      if(store) begin
	memWriteReg<=0;
      end
      
      else begin //I don't think I actually have to do anything.
	cWriteReg<=0;
      end
    end
    
  end //End of state 1 stuff.
  
  //Beginning of state 0 stuff:
  else begin 
    if(fetchNextOp) begin
      addrMuxSelector<=2'b00;
      curVals<=MEMDAT;
      cWriteReg<=0;
      stkpWrite<=0;
      //pcInc<=0;
      pcInputSel<=0;
    end
    
    else if(ldl) begin
      curVals<=0;//MEMDAT;
      cSelector<=1;
      cWriteReg<=1;
    end
    
    else if(cmp) begin
      curVals<=0;//MEMDAT;
      gFlag<=greater;
      lFlag<=less;
      sFlag<=same;
    end
    
    //Now for branches:
    else if(branch) begin
      if(op==51) begin//Unconditional jump
	pcWrite<=1;
	//curVals<=MEMDAT;
	curVals<=0; //Insert a NOP so that we go back to the first state.
      end
      
      else if(op==52) begin //Jump on equal
	if(same) begin
	  pcWrite<=1;
	  curVals<=0; //Same as above.
	end
	
	else begin
	  curVals<=MEMDAT;
	end
	
      end
      
      else if(op==53) begin //Jump on positive
	if(greater) begin
	  pcWrite<=1;
	  curVals<=0;
	end
	
	else begin
	  curVals<=MEMDAT;
	end
      end
      
      else if(op==54) begin //Jump on negative
	if(less) begin
	  pcWrite<=1;
	  curVals<=0;
	end
	
	else begin
	  curVals<=MEMDAT;
	end
      end
    end
    
    //Now catch any stack loads/stores:
    else if(op==40) begin //Store Stack Register
      cSelector<=2;
      cWriteReg<=1;
      curVals<=0;
    end
    
    else if(op==41) begin //Load Stack Register
      stkpWrite<=1;
      curVals<=0;
    end
    
    else if(op==44) begin //Call. This instruction will definitely 
		    //Limit clockspeed potential.
      addrMuxSelector<=2'b10;
      stkpDec<=1;
      //stateReg<=1;
      memOutReg<=PCBus[15:0]; //Write the 16 lowest bits of the program counter.
      memWriteReg<=1;
    end
    
    else if(op==55) begin //Ret
      stkpInc<=1;
      addrMuxSelector<=2'b10;
      pcInputSel<=1; //Set the input to the memory bus.
      pcWrite<=1;
      curVals<=MEMDAT;
    end
    
    //Now for loads/stores:
    else if(stack) begin
      stateReg<=1;
      addrMuxSelector<=2'b10;
      if(store) begin
	memWriteReg<=1'b1;
	stkpDec<=1;
	memOutReg<=CDAT;
      end
      
      else begin
	stkpInc<=1;
      end
    end
    
    else if(~stack) begin
      stateReg<=1;
      addrMuxSelector<=2'b01;
      
      if(store) begin
	memWriteReg<=1'b1;
	memOutReg<=CDAT;
      end
      
      else begin
	cSelector<=0;
	cWriteReg<=1;
      end
    end
  end //End of state 0 stuff.
end

initial begin
  curVals<=0;
  addrMuxSelector<=0;
  stateReg<=0;
  memWriteReg<=0;
  memOutReg<=0;
  cSelector<=0;
  cWriteReg<=0;
  pcWrite<=0;
end

endmodule

dispatchu_tb.v
//Testbench for the dispatch unit.
module dispatchu_tb(
  );

reg clk;
reg [15:0] aDat;
reg [15:0] bDat;
reg [15:0] cDat;
wire [31:0] addr;
wire [15:0] memOut;
wire memWrite;
wire [15:0] cOut;
wire cWrite;
wire [2:0] aSel;
wire [2:0] bSel;
wire [2:0] cSel;
wire [3:0] intOp;
wire [2:0] intA;
wire [2:0] intB;
wire [2:0] intC;

wire [15:0] memDat;

//Make a small, 16 word memory to play with.
reg [15:0] memoryArray[15:0]; 
reg [3:0] memSel;
assign memDat=memoryArray[memSel];

dispatchu du(clk, memDat, aDat, bDat, cDat, addr, memOut, memWrite, cOut, cWrite, aSel, bSel, cSel, intOp, intA, intB, intC);


initial begin
//Set up the virtual memory space:
  clk=0;
  aDat=0;
  bDat=0;
  cDat=0;
  memSel=0;
  memoryArray[0]=16'h000a;
  memoryArray[1]=16'h8007;
  memoryArray[2]=16'h6638;
end

always begin
  #1 clk<=!clk;
  if(clk) begin
    if(memWrite) begin
      memoryArray[addr%16]<=memOut;
    end
      
    else begin
      memSel<=addr%16;
    end
  end
end

initial begin
  $dumpfile("dispatchu_tb.vcd");
  $dumpvars;
end

initial 
  #128 $finish;
endmodule

old/dispatchu_tb.vcd
$date
	Fri Nov 13 07:49:37 2015
$end
$version
	Icarus Verilog
$end
$timescale
	1s
$end
$scope module dispatchu_tb $end
$var wire 3 ! aSel [2:0] $end
$var wire 32 " addr [31:0] $end
$var wire 3 # bSel [2:0] $end
$var wire 16 $ cOut [15:0] $end
$var wire 3 % cSel [2:0] $end
$var wire 1 & cWrite $end
$var wire 3 ' intA [2:0] $end
$var wire 3 ( intB [2:0] $end
$var wire 3 ) intC [2:0] $end
$var wire 4 * intOp [3:0] $end
$var wire 16 + memDat [15:0] $end
$var wire 16 , memOut [15:0] $end
$var wire 1 - memWrite $end
$var reg 16 . aDat [15:0] $end
$var reg 16 / bDat [15:0] $end
$var reg 16 0 cDat [15:0] $end
$var reg 1 1 clk $end
$var reg 4 2 memSel [3:0] $end
$scope module du $end
$var wire 32 3 ABBus [31:0] $end
$var wire 16 4 ADAT [15:0] $end
$var wire 3 5 Asel [2:0] $end
$var wire 16 6 BDAT [15:0] $end
$var wire 3 7 Bsel [2:0] $end
$var wire 16 8 CDAT [15:0] $end
$var wire 1 9 CLK $end
$var wire 16 : Cout [15:0] $end
$var wire 3 ; Csel [2:0] $end
$var wire 16 < MEMDAT [15:0] $end
$var wire 32 = PCBus [31:0] $end
$var wire 3 > a [2:0] $end
$var wire 32 ? addr [31:0] $end
$var wire 3 @ b [2:0] $end
$var wire 1 A branch $end
$var wire 3 B c [2:0] $end
$var wire 1 & cWrite $end
$var wire 1 C cmp $end
$var wire 32 D extendedMemoryInputBus [31:0] $end
$var wire 1 E fetchNextOp $end
$var wire 1 F greater $end
$var wire 1 G intOp $end
$var wire 3 H intPipeA [2:0] $end
$var wire 3 I intPipeB [2:0] $end
$var wire 3 J intPipeC [2:0] $end
$var wire 4 K intPipeOp [3:0] $end
$var wire 1 L ldl $end
$var wire 1 M less $end
$var wire 1 N load $end
$var wire 16 O memOut [15:0] $end
$var wire 1 - memWrite $end
$var wire 7 P op [6:0] $end
$var wire 1 Q pcDec $end
$var wire 1 R pcInc $end
$var wire 1 S same $end
$var wire 1 T stack $end
$var wire 32 U stkPtrBus [31:0] $end
$var wire 1 V store $end
$var reg 2 W addrMuxSelector [1:0] $end
$var reg 2 X cSelector [1:0] $end
$var reg 1 Y cWriteReg $end
$var reg 16 Z curVals [15:0] $end
$var reg 1 [ gFlag $end
$var reg 1 \ lFlag $end
$var reg 16 ] memOutReg [15:0] $end
$var reg 1 ^ memWriteReg $end
$var reg 1 _ pcInputSel $end
$var reg 1 ` pcWrite $end
$var reg 1 a sFlag $end
$var reg 1 b stateReg $end
$var reg 1 c stkpDec $end
$var reg 1 d stkpInc $end
$var reg 1 e stkpWrite $end
$scope module stackPointer $end
$var wire 1 9 CLK $end
$var wire 1 f DECREMENT $end
$var wire 1 g INCREMENT $end
$var wire 32 h NEWV [31:0] $end
$var wire 1 i WRITE $end
$var wire 32 j out [31:0] $end
$var reg 32 k val [31:0] $end
$upscope $end
$scope module programCounter $end
$var wire 1 9 CLK $end
$var wire 1 Q DECREMENT $end
$var wire 1 R INCREMENT $end
$var wire 32 l NEWV [31:0] $end
$var wire 1 m WRITE $end
$var wire 32 n out [31:0] $end
$var reg 32 o val [31:0] $end
$upscope $end
$scope module ot $end
$var wire 7 p OP [6:0] $end
$var wire 1 A branch $end
$var wire 1 C cmp $end
$var wire 1 L ldl $end
$var wire 1 N load $end
$var wire 1 T stack $end
$var wire 1 V store $end
$upscope $end
$scope module comp $end
$var wire 16 q A [15:0] $end
$var wire 16 r B [15:0] $end
$var wire 1 F greater $end
$var wire 1 M less $end
$var wire 1 S same $end
$upscope $end
$upscope $end
$upscope $end
$enddefinitions $end
#0
$dumpvars
b0 r
b0 q
b0 p
b0 o
b0 n
0m
bx l
b0 k
b0 j
xi
b0 h
xg
xf
xe
xd
xc
0b
xa
0`
x_
0^
b0 ]
x\
x[
b0 Z
0Y
b0 X
b0 W
0V
b0 U
0T
1S
1R
0Q
b0 P
b0 O
0N
0M
0L
b0 K
b0 J
b0 I
b0 H
1G
0F
1E
b1010 D
0C
b0 B
0A
b0 @
b0 ?
b0 >
b0 =
b1010 <
b0 ;
b1010 :
09
b0 8
b0 7
b0 6
b0 5
b0 4
b0 3
b0 2
01
b0 0
b0 /
b0 .
0-
b0 ,
b1010 +
b0 *
b0 )
b0 (
b0 '
0&
b0 %
b1010 $
b0 #
b0 "
b0 !
$end
#1
b1 @
b1 (
b1 I
b1 #
b1 7
b10 B
b10 )
b10 J
b10 %
b10 ;
0_
b0 l
0e
0i
b1010 Z
11
19
#2
b1 o
b1 =
b1 n
b1 "
b1 ?
01
09
#3
11
19
#4
b10 o
b10 =
b10 n
b10 "
b10 ?
b1 2
b1000000000000111 +
b1000000000000111 <
b1000000000000111 D
b1000000000000111 $
b1000000000000111 :
01
09
#5
0R
0E
0G
1L
b1000000 P
b1000000 p
b0 @
b0 (
b0 I
b0 #
b0 7
b111 B
b111 )
b111 J
b111 %
b111 ;
b1000000000000111 Z
11
19
#6
b10 2
b110011000111000 +
b110011000111000 <
b110011000111000 D
b110011000111000 $
b110011000111000 :
01
09
#7
1R
1E
1G
0L
b0 P
b0 p
b0 B
b0 )
b0 J
b0 %
b0 ;
1Y
1&
b1 X
b0 $
b0 :
b0 Z
11
19
#8
b11 o
b11 =
b11 n
b11 "
b11 ?
01
09
#9
0R
0E
0G
b0 *
b0 K
1A
b110011 P
b110011 p
b111 @
b111 (
b111 I
b111 #
b111 7
b110011000111000 $
b110011000111000 :
0Y
0&
b110011000111000 Z
11
19
#10
b11 2
bx +
bx <
b0xxxxxxxxxxxxxxxx D
01
09
#11
1R
1E
1G
0A
b0 P
b0 p
b0 @
b0 (
b0 I
b0 #
b0 7
b0 $
b0 :
b0 Z
1`
1m
11
19
#12
b0 o
b0 =
b0 n
b0 "
b0 ?
01
09
#13
xR
xE
xG
bx *
bx K
xL
xT
xA
xN
xV
xC
bx P
bx p
bx >
bx '
bx H
bx !
bx 5
bx @
bx (
bx I
bx #
bx 7
bx B
bx )
bx J
bx %
bx ;
b0xxxxxxxxxxxxxxx $
b0xxxxxxxxxxxxxxx :
bx Z
11
19
#14
b0 2
b1010 +
b1010 <
b1010 D
01
09
